[{"Rank":1,"Search":"Jimmy Carter","scraped_datetime":"2024_12_30_23","Search_var":"jimmy carter "},{"Rank":2,"Search":"Leicester City vs Man City","scraped_datetime":"2024_12_30_23","Search_var":"leicester city vs man city "},{"Rank":3,"Search":"Rohit Sharma","scraped_datetime":"2024_12_30_23","Search_var":"rohit sharma "},{"Rank":4,"Search":"Dorian Finney-Smith","scraped_datetime":"2024_12_30_23","Search_var":"dorian finneysmith "},{"Rank":5,"Search":"Tottenham vs Wolves","scraped_datetime":"2024_12_30_23","Search_var":"tottenham vs wolves "},{"Rank":6,"Search":"Rishabh Pant","scraped_datetime":"2024_12_30_23","Search_var":"rishabh pant "},{"Rank":7,"Search":"Air Canada","scraped_datetime":"2024_12_30_23","Search_var":"air canada "},{"Rank":8,"Search":"Airplane","scraped_datetime":"2024_12_30_23","Search_var":"airplane "},{"Rank":9,"Search":"Endometriosis","scraped_datetime":"2024_12_30_23","Search_var":"endometriosis "},{"Rank":10,"Search":"Leeds United","scraped_datetime":"2024_12_30_23","Search_var":"leeds united "},{"Rank":11,"Search":"Fireworks","scraped_datetime":"2024_12_30_23","Search_var":"fireworks "},{"Rank":12,"Search":"New Year's Eve","scraped_datetime":"2024_12_30_23","Search_var":"new years eve "},{"Rank":13,"Search":"Jeju Air","scraped_datetime":"2024_12_30_23","Search_var":"jeju air "},{"Rank":14,"Search":"Brisbane International","scraped_datetime":"2024_12_30_23","Search_var":"brisbane international "},{"Rank":15,"Search":"Nick Kyrgios","scraped_datetime":"2024_12_30_23","Search_var":"nick kyrgios "},{"Rank":16,"Search":"Plane crash","scraped_datetime":"2024_12_30_23","Search_var":"plane crash "},{"Rank":17,"Search":"Mitchell Marsh","scraped_datetime":"2024_12_30_23","Search_var":"mitchell marsh "},{"Rank":18,"Search":"Bumrah","scraped_datetime":"2024_12_30_23","Search_var":"bumrah "},{"Rank":19,"Search":"Hanukkah","scraped_datetime":"2024_12_30_23","Search_var":"hanukkah "},{"Rank":20,"Search":"Dayle Haddon","scraped_datetime":"2024_12_30_23","Search_var":"dayle haddon "}]