[{"publication":"bbc","scraped_datetime":"2025_12_04_09","Headline":"Drunk raccoon found passed out on liquor store floor after breaking in","Url":"\/news\/articles\/cy8jnxxm70jo","Rank":1,"Search_var":"drunk raccoon found passed out on liquor store floor after breaking in "},{"publication":"bbc","scraped_datetime":"2025_12_04_09","Headline":"What latest Ukraine talks reveal about Putin's state of mind","Url":"\/news\/articles\/cpq4e21nr5vo","Rank":2,"Search_var":"what latest ukraine talks reveal about putins state of mind "},{"publication":"bbc","scraped_datetime":"2025_12_04_09","Headline":"Santa signs prompt calls to police in Canadian city","Url":"\/news\/articles\/cj9y3ee8wzlo","Rank":3,"Search_var":"santa signs prompt calls to police in canadian city "},{"publication":"bbc","scraped_datetime":"2025_12_04_09","Headline":"'No excuse' - California doctor sentenced to 30 months in Matthew Perry overdose case","Url":"\/news\/articles\/cy7v0gpv2pgo","Rank":4,"Search_var":"no excuse  california doctor sentenced to 30 months in matthew perry overdose case "},{"publication":"bbc","scraped_datetime":"2025_12_04_09","Headline":"Zelensky says Ukraine and US negotiators will meet after Russia visit","Url":"\/news\/articles\/c7731n5z6d3o","Rank":5,"Search_var":"zelensky says ukraine and us negotiators will meet after russia visit "},{"publication":"bbc","scraped_datetime":"2025_12_04_09","Headline":"Previously unseen images of Epstein's island released","Url":"\/news\/articles\/c4g5rrlve33o","Rank":6,"Search_var":"previously unseen images of epsteins island released "},{"publication":"bbc","scraped_datetime":"2025_12_04_09","Headline":"'Carspreading' is on the rise - and not everyone is happy about it","Url":"\/news\/articles\/cy7vdvl2531o","Rank":7,"Search_var":"carspreading is on the rise  and not everyone is happy about it "},{"publication":"bbc","scraped_datetime":"2025_12_04_09","Headline":"A 355-year-old Royal Charter that survived the blitz auctioned for $13m in Canada","Url":"\/news\/articles\/cg4nvr3e1v0o","Rank":8,"Search_var":"a 355yearold royal charter that survived the blitz auctioned for 13m in canada "},{"publication":"bbc","scraped_datetime":"2025_12_04_09","Headline":"Trump says he is pardoning Democratic congressman in bribery case","Url":"\/news\/articles\/c62v9z7z1z2o","Rank":9,"Search_var":"trump says he is pardoning democratic congressman in bribery case "},{"publication":"bbc","scraped_datetime":"2025_12_04_09","Headline":"US Homeland Security secretary calls for more travel bans","Url":"\/news\/articles\/c79x3rwxjryo","Rank":10,"Search_var":"us homeland security secretary calls for more travel bans "}]