[{"publication":"Bsky","scraped_datetime":"2025_12_06_11","Topic":"ROH Final Battle","Url":"\/profile\/trending.bsky.app\/feed\/517202517","Rank":1,"Search_var":"roh final battle "},{"publication":"Bsky","scraped_datetime":"2025_12_06_11","Topic":"Olivia Nuzzi","Url":"\/profile\/trending.bsky.app\/feed\/516969133","Rank":2,"Search_var":"olivia nuzzi "},{"publication":"Bsky","scraped_datetime":"2025_12_06_11","Topic":"World Cup Draw","Url":"\/profile\/trending.bsky.app\/feed\/516702146","Rank":3,"Search_var":"world cup draw "},{"publication":"Bsky","scraped_datetime":"2025_12_06_11","Topic":"Gianni Infantino","Url":"\/profile\/trending.bsky.app\/feed\/516739441","Rank":4,"Search_var":"gianni infantino "},{"publication":"Bsky","scraped_datetime":"2025_12_06_11","Topic":"CDC Panel","Url":"\/profile\/trending.bsky.app\/feed\/516614359","Rank":5,"Search_var":"cdc panel "}]