[{"publication": "ABC", "scraped_datetime": "2023_12_04_11", "Headline": "Outrage in Ballarat at white supremacist march, 15yo questioned over banned Nazi salute", "Url": "https://www.abc.net.au/news/2023-12-04/ballarat-white-supremacy-march-investigated/103183616", "Rank": 1, "Search_var": "outrage in ballarat at white supremacist march 15yo questioned over banned nazi salute "}, {"publication": "ABC", "scraped_datetime": "2023_12_04_11", "Headline": "Man remains in critical condition after being buried alive in sand on Bribie Island", "Url": "https://www.abc.net.au/news/2023-12-04/josh-taylor-buried-alive-sand-bribie-island-moreton-bay/103183644", "Rank": 2, "Search_var": "man remains in critical condition after being buried alive in sand on bribie island "}, {"publication": "ABC", "scraped_datetime": "2023_12_04_11", "Headline": "Faced with 'certain death', pathologist Richard Scolyer is undergoing an experimental treatment", "Url": "https://www.abc.net.au/news/2023-12-04/richard-scolyer-experimental-treatment-australian-story/103098422", "Rank": 3, "Search_var": "faced with certain death pathologist richard scolyer is undergoing an experimental treatment "}, {"publication": "ABC", "scraped_datetime": "2023_12_04_11", "Headline": "'We all got AI-ed': The Australian jobs being lost to AI under the radar", "Url": "https://www.abc.net.au/news/2023-12-04/australian-jobs-being-lost-to-ai/103123682", "Rank": 4, "Search_var": "we all got aied the australian jobs being lost to ai under the radar "}, {"publication": "ABC", "scraped_datetime": "2023_12_04_11", "Headline": "'Amoral': Catholic education head takes issue with national sexual consent curriculum", "Url": "https://www.abc.net.au/news/2023-12-04/catholic-education-gerard-gaskin-consent-education/103175500", "Rank": 5, "Search_var": "amoral catholic education head takes issue with national sexual consent curriculum "}]