[{"publication": "ABC", "scraped_datetime": "2023_07_29_07", "Headline": "Charlotte Owen is the youngest peer in the House of Lords. But the newly minted baroness is outraging Britain", "Url": "https://www.abc.net.au/news/2023-07-29/charlotte-owen-becomes-youngest-peer-in-britains-house-of-lords/102655596", "Rank": 1}, {"publication": "ABC", "scraped_datetime": "2023_07_29_07", "Headline": "When a mum breastfeeding her baby sparks outrage, we're focusing on the wrong things", "Url": "https://www.abc.net.au/news/2023-07-29/trans-mum-breastfeeding-anger/102659824", "Rank": 2}, {"publication": "ABC", "scraped_datetime": "2023_07_29_07", "Headline": "Five quick hits \u2014 Steve Smith's great run-out escape and Joe Root's stunning catch", "Url": "https://www.abc.net.au/news/2023-07-29/five-quick-hits-day-two-ashes-fifth-test-the-oval/102663406", "Rank": 3}, {"publication": "ABC", "scraped_datetime": "2023_07_29_07", "Headline": "Trump took boxes of classified documents home and kept them next to his toilet. Here's why it could land him in jail", "Url": "https://www.abc.net.au/news/2023-07-29/how-trump-could-go-to-jail-over-classified-documents/102660154", "Rank": 4}, {"publication": "ABC", "scraped_datetime": "2023_07_29_07", "Headline": "A weary Australia is limping towards the Ashes finish line, but a spirited fightback has kept it alive", "Url": "https://www.abc.net.au/news/2023-07-29/australia-limps-to-ashes-finish-line-still-alive-at-the-oval/102663506", "Rank": 5}]