[{"publication":"ABC","scraped_datetime":"2025_11_24_19","Headline":"Senate shut down for 1.5 hours after Pauline Hanson's burka stunt","Url":"https:\/\/www.abc.net.au\/news\/2025-11-24\/senate-suspended-after-pauline-hansons-burka-stunt\/106047124","Rank":1,"Search_var":"senate shut down for 15 hours after pauline hansons burka stunt "},{"publication":"ABC","scraped_datetime":"2025_11_24_19","Headline":"Teenage boy dies in stabbing at reserve in Sydney's north-west","Url":"https:\/\/www.abc.net.au\/news\/2025-11-24\/teenage-boy-dies-in-stabbing-at-rouse-hill-reserve\/106047158","Rank":2,"Search_var":"teenage boy dies dy in stabbing at reserve in sydneys northwest "},{"publication":"ABC","scraped_datetime":"2025_11_24_19","Headline":"BOM boss reveals $96.5m website rebuild approved by Turnbull government","Url":"https:\/\/www.abc.net.au\/news\/2025-11-24\/bom-website-approved-by-coalition-ceo-says\/106047518","Rank":3,"Search_var":"bom boss reveals 965m website rebuild approved by turnbull government "},{"publication":"ABC","scraped_datetime":"2025_11_24_19","Headline":"Trump putting America first could be a priceless gift to Australia","Url":"https:\/\/www.abc.net.au\/news\/2025-11-24\/trump-presidency-could-be-priceless-gift-australia-boyer-lecture\/106028102","Rank":4,"Search_var":"trump putting america first could be a priceless gift to australia "},{"publication":"ABC","scraped_datetime":"2025_11_24_19","Headline":"More than 150,000 without power as 11cm hail falls in Qld","Url":"https:\/\/www.abc.net.au\/news\/2025-11-24\/thunderstorm-warning-qld-hail-extreme-weather\/106046398","Rank":5,"Search_var":"more than 150000 without power as 11cm hail falls in qld "},{"publication":"ABC","scraped_datetime":"2025_11_24_19","Headline":"NSW bushwalker found dead in Tasmanian wilderness","Url":"https:\/\/www.abc.net.au\/news\/2025-11-24\/bushwalker-finds-body-of-nsw-man-at-federation-peak-tasmania\/106047444","Rank":6,"Search_var":"nsw bushwalker found dead in tasmanian wilderness "}]