[{"publication":"ABC","scraped_datetime":"2026_01_19_15","Headline":"Former Labor strategist Tim Picton dies after alleged assault","Url":"https:\/\/www.abc.net.au\/news\/2026-01-19\/tim-picton-dies-three-weeks-after-nightclub-assault\/106244678","Rank":1,"Search_var":"former labor strategist tim picton dies dy after alleged assault "},{"publication":"ABC","scraped_datetime":"2026_01_19_15","Headline":"Young surfer uninjured after shark bites board at Sydney beach","Url":"https:\/\/www.abc.net.au\/news\/2026-01-19\/nsw-young-surfer-second-sydney-beach-shark-encounter\/106245088","Rank":2,"Search_var":"young surfer uninjured after shark bites board at sydney beach "},{"publication":"ABC","scraped_datetime":"2026_01_19_15","Headline":"De Minaur wins, Aussie wildcard's opponent forced off in wheelchair","Url":"https:\/\/www.abc.net.au\/news\/2026-01-19\/australian-open-2026-live-alex-de-minaur-novak-djokovic\/106243798","Rank":3,"Search_var":"de minaur wins aussie wildcards opponent forced off in wheelchair "},{"publication":"ABC","scraped_datetime":"2026_01_19_15","Headline":"Company director sentenced for interfering with Aboriginal relics","Url":"https:\/\/www.abc.net.au\/news\/2026-01-19\/graeme-elphinstone-allegations-interfere-with-aboriginal-sites\/106243968","Rank":4,"Search_var":"company director sentenced for interfering with aboriginal relics "},{"publication":"ABC","scraped_datetime":"2026_01_19_15","Headline":"Dingoes 'had been in contact' with deceased woman's body on K'gari beach","Url":"https:\/\/www.abc.net.au\/news\/2026-01-19\/police-investigating-death-of-woman-on-kgari-fraser-island\/106244106","Rank":5,"Search_var":"dingoes had been in contact with deceased womans body on kgari beach "},{"publication":"ABC","scraped_datetime":"2026_01_19_15","Headline":"Greenland tensions escalate as US threatens tariffs over European troops","Url":"https:\/\/www.abc.net.au\/news\/2026-01-19\/us-tariff-threats-european-troops-sent-to-greenland\/106243860","Rank":6,"Search_var":"greenland tensions escalate as us threatens tariffs over european troops "}]