[{"publication":"ABC","scraped_datetime":"2026_05_05_21","Headline":"Indigenous commissioner condemns comedian's 'deeply offensive' video","Url":"https:\/\/www.abc.net.au\/news\/2026-05-05\/indigenous-commissioner-condemns-comedian-video\/106645610","Rank":1,"Search_var":"indigenous commissioner condemns comedians deeply offensive video "},{"publication":"ABC","scraped_datetime":"2026_05_05_21","Headline":"'Police can't help you': The threat issued to Melbourne's pub and club owners","Url":"https:\/\/www.abc.net.au\/news\/2026-05-05\/threatening-sms-fire-bombings-illicit-alcohol-melbourne-pub-wars\/106644480","Rank":2,"Search_var":"police cant help you the threat issued to melbournes pub and club owners "},{"publication":"ABC","scraped_datetime":"2026_05_05_21","Headline":"Five things you can do to save money now that interest rates have gone up","Url":"https:\/\/www.abc.net.au\/news\/2026-05-05\/interest-rates-explainer-emily-stewart\/106627224","Rank":3,"Search_var":"five things you can do to save money now that interest rates have gone up "},{"publication":"ABC","scraped_datetime":"2026_05_05_21","Headline":"Firefighter pulled knife on Jewish paramedic, royal commission told","Url":"https:\/\/www.abc.net.au\/news\/2026-05-05\/bondi-antisemitism-social-cohesion-royal-commission-paramedic\/106644084","Rank":4,"Search_var":"firefighter pulled knife on jewish paramedic royal commission told "},{"publication":"ABC","scraped_datetime":"2026_05_05_21","Headline":"Human-to-human transmission suspected in deadly hantavirus outbreak","Url":"https:\/\/www.abc.net.au\/news\/2026-05-05\/who-suspects-hantavirus-human-to-human-transmission\/106645684","Rank":5,"Search_var":"humantohuman transmission suspected in deadly hantavirus outbreak "},{"publication":"ABC","scraped_datetime":"2026_05_05_21","Headline":"'I have lost basically everything': Ex-AFL player opens up on compensation fight","Url":"https:\/\/www.abc.net.au\/news\/2026-05-05\/ex-afl-player-opens-up-on-brain-trauma-compensation-fight\/106636178","Rank":6,"Search_var":"i have lost basically everything exafl player opens up on compensation fight "}]